wcpan/drive/cli/__init__.py
wcpan/drive/cli/__main__.py
wcpan/drive/cli/_cfg.py
wcpan/drive/cli/_cmd/__init__.py
wcpan/drive/cli/_cmd/auth.py
wcpan/drive/cli/_cmd/download.py
wcpan/drive/cli/_cmd/find.py
wcpan/drive/cli/_cmd/info.py
wcpan/drive/cli/_cmd/lib.py
wcpan/drive/cli/_cmd/list_.py
wcpan/drive/cli/_cmd/mkdir.py
wcpan/drive/cli/_cmd/move.py
wcpan/drive/cli/_cmd/remove.py
wcpan/drive/cli/_cmd/shell.py
wcpan/drive/cli/_cmd/sync.py
wcpan/drive/cli/_cmd/trash.py
wcpan/drive/cli/_cmd/tree.py
wcpan/drive/cli/_cmd/upload.py
wcpan/drive/cli/_cmd/usage.py
wcpan/drive/cli/_download.py
wcpan/drive/cli/_interaction.py
wcpan/drive/cli/_lib.py
wcpan/drive/cli/_main.py
wcpan/drive/cli/_queue.py
wcpan/drive/cli/_upload.py
wcpan/drive/cli/lib.py
wcpan/drive/cli/py.typed
wcpan_drive_cli-3.9.0.dist-info/METADATA
wcpan_drive_cli-3.9.0.dist-info/WHEEL
wcpan_drive_cli-3.9.0.dist-info/entry_points.txt
wcpan_drive_cli-3.9.0.dist-info/licenses/LICENSE.txt
wcpan_drive_cli-3.9.0.dist-info/RECORD
