Metadata-Version: 2.4
Name: wcpan-drive-cli
Version: 3.9.0
Summary: command line tool for wcpan.drive
License-Expression: MIT
License-File: LICENSE.txt
Author: Wei-Cheng Pan
Author-email: legnaleurc@gmail.com
Requires-Python: >=3.12,<4.0
Classifier: Development Status :: 3 - Alpha
Classifier: Intended Audience :: Developers
Classifier: Operating System :: OS Independent
Classifier: Programming Language :: Python :: 3
Classifier: Programming Language :: Python :: 3.12
Classifier: Programming Language :: Python :: 3.13
Classifier: Programming Language :: Python :: 3.14
Classifier: Typing :: Typed
Requires-Dist: PyYAML (>=6.0.1,<7.0.0)
Requires-Dist: pymediainfo (>=7.0.1,<8.0.0)
Requires-Dist: python-magic (>=0.4.27,<0.5.0)
Requires-Dist: wcpan-drive-core (>=4.1.0,<5.0.0)
Requires-Dist: wcpan-logging (>=2.0.3,<3.0.0)
Requires-Dist: wcpan-queue (>=7.2.1,<8.0.0)
